jarvis/__init__.py
jarvis/__main__.py
jarvis/events.py
jarvis/google_imgs.py
jarvis/jconfig.py
jarvis/utils.py
jarvis/function/__init__.py
jarvis/function/jarvisfunction.py
jarvisub-1.3b0.dist-info/LICENSE
jarvisub-1.3b0.dist-info/METADATA
jarvisub-1.3b0.dist-info/WHEEL
jarvisub-1.3b0.dist-info/top_level.txt
jarvisub-1.3b0.dist-info/RECORD
