Metadata-Version: 2.1
Name: jarvisub
Version: 1.3b0
Summary: A Secure and Powerful Python-Telethon Based Library For Ultroid Userbot.
Home-page: https://github.com/Jarvis-Works/JarvisUserbot
Author: Spidy
Author-email: me@sppidy.me
License: GNU AFFERO GENERAL PUBLIC LICENSE (v3)
Platform: UNKNOWN
Classifier: Programming Language :: Python :: 3
Classifier: License :: OSI Approved :: GNU General Public License v3 (GPLv3)
Classifier: Operating System :: OS Independent
Requires-Python: >=3.6
Requires-Dist: Pillow (>=5.3.0)
Requires-Dist: PyGithub
Requires-Dist: PyLyrics
Requires-Dist: PyPDF2
Requires-Dist: aiofiles
Requires-Dist: aiohttp (>=3.6.2)
Requires-Dist: apscheduler
Requires-Dist: async-generator
Requires-Dist: beautifulsoup4 (>=4.9.1)
Requires-Dist: bs4
Requires-Dist: bwb (==3.0.0)
Requires-Dist: cfscrape
Requires-Dist: coffeehouse
Requires-Dist: covid
Requires-Dist: cowpy
Requires-Dist: cryptg
Requires-Dist: dnspython
Requires-Dist: emoji
Requires-Dist: gTTS-token (>=1.1.3)
Requires-Dist: gTTS (>=2.0.1)
Requires-Dist: geopy
Requires-Dist: gitpython
Requires-Dist: glitch-this
Requires-Dist: google-api-python-client (==1.12.8)
Requires-Dist: google-auth-oauthlib
Requires-Dist: google-images-download (>=2.7.1)
Requires-Dist: googletrans (==4.0.0rc1)
Requires-Dist: gsearch
Requires-Dist: hachoir
Requires-Dist: heroku3
Requires-Dist: httplib2
Requires-Dist: humanize
Requires-Dist: lottie
Requires-Dist: lxml (>=4.5.2)
Requires-Dist: lyricsgenius
Requires-Dist: nospamplus
Requires-Dist: oauth2client
Requires-Dist: psutil
Requires-Dist: psycopg2-binary
Requires-Dist: pySmartDL
Requires-Dist: pybase64 (>=0.4.0)
Requires-Dist: pyfiglet
Requires-Dist: pylast
Requires-Dist: pymongo
Requires-Dist: pyrogram
Requires-Dist: python-barcode
Requires-Dist: python-decouple (==3.3)
Requires-Dist: python-dotenv
Requires-Dist: python-dotenv (==0.15.0)
Requires-Dist: python-magic
Requires-Dist: pytube
Requires-Dist: pytz
Requires-Dist: qrcode
Requires-Dist: redis
Requires-Dist: regex
Requires-Dist: requests (>=2.18.4)
Requires-Dist: search-engine-parser (>=0.4.2)
Requires-Dist: selenium
Requires-Dist: speedtest-cli (>=2.0.2)
Requires-Dist: sqlalchemy (>=1.2)
Requires-Dist: telegraph
Requires-Dist: telethon (==1.19.1)
Requires-Dist: telethon (>=1.19.5)
Requires-Dist: tswift
Requires-Dist: urbandict (>=0.5)
Requires-Dist: validators
Requires-Dist: wikipedia (>=1.4.0)
Requires-Dist: youtube-dl
